keyspot/__init__.py
keyspot-2.0.0.dist-info/LICENSE
keyspot-2.0.0.dist-info/METADATA
keyspot-2.0.0.dist-info/WHEEL
keyspot-2.0.0.dist-info/top_level.txt
keyspot-2.0.0.dist-info/RECORD
