Metadata-Version: 2.1
Name: keyspot
Version: 2.0.0
Summary: Environment variable manager for python
Home-page: https://github.com/KeySpot/python-api
Author: Carl Schader
Author-email: carlschader@gmail.com
License: UNKNOWN
Project-URL: Bug Tracker, https://github.com/KeySpot/python-api/issues
Platform: UNKNOWN
Classifier: Programming Language :: Python :: 3
Classifier: License :: OSI Approved :: MIT License
Classifier: Operating System :: OS Independent
Requires-Python: >=3.6
License-File: LICENSE
